{
   "html_attributions" : [],
   "result" : {
      "address_components" : [
         {
            "long_name" : "310",
            "short_name" : "310",
            "types" : [ "street_number" ]
         },
         {
            "long_name" : "Edwin Drive",
            "short_name" : "Edwin Dr",
            "types" : [ "route" ]
         },
         {
            "long_name" : "Virginia Beach",
            "short_name" : "Virginia Beach",
            "types" : [ "locality", "political" ]
         },
         {
            "long_name" : "Virginia",
            "short_name" : "VA",
            "types" : [ "administrative_area_level_1", "political" ]
         },
         {
            "long_name" : "United States",
            "short_name" : "US",
            "types" : [ "country", "political" ]
         },
         {
            "long_name" : "23462",
            "short_name" : "23462",
            "types" : [ "postal_code" ]
         },
         {
            "long_name" : "4523",
            "short_name" : "4523",
            "types" : [ "postal_code_suffix" ]
         }
      ],
      "adr_address" : "\u003cspan class=\"street-address\"\u003e310 Edwin Dr\u003c/span\u003e, \u003cspan class=\"locality\"\u003eVirginia Beach\u003c/span\u003e, \u003cspan class=\"region\"\u003eVA\u003c/span\u003e \u003cspan class=\"postal-code\"\u003e23462-4523\u003c/span\u003e, \u003cspan class=\"country-name\"\u003eUSA\u003c/span\u003e",
      "business_status" : "OPERATIONAL",
      "current_opening_hours" : {
         "open_now" : true,
         "periods" : [
            {
               "close" : {
                  "date" : "2022-12-04",
                  "day" : 0,
                  "time" : "1700"
               },
               "open" : {
                  "date" : "2022-12-04",
                  "day" : 0,
                  "time" : "0630"
               }
            },
            {
               "close" : {
                  "date" : "2022-12-05",
                  "day" : 1,
                  "time" : "1700"
               },
               "open" : {
                  "date" : "2022-12-05",
                  "day" : 1,
                  "time" : "0630"
               }
            },
            {
               "close" : {
                  "date" : "2022-12-06",
                  "day" : 2,
                  "time" : "1700"
               },
               "open" : {
                  "date" : "2022-12-06",
                  "day" : 2,
                  "time" : "0630"
               }
            },
            {
               "close" : {
                  "date" : "2022-12-07",
                  "day" : 3,
                  "time" : "1700"
               },
               "open" : {
                  "date" : "2022-12-07",
                  "day" : 3,
                  "time" : "0630"
               }
            },
            {
               "close" : {
                  "date" : "2022-12-08",
                  "day" : 4,
                  "time" : "1700"
               },
               "open" : {
                  "date" : "2022-12-08",
                  "day" : 4,
                  "time" : "0630"
               }
            },
            {
               "close" : {
                  "date" : "2022-12-09",
                  "day" : 5,
                  "time" : "1700"
               },
               "open" : {
                  "date" : "2022-12-09",
                  "day" : 5,
                  "time" : "0630"
               }
            },
            {
               "close" : {
                  "date" : "2022-12-03",
                  "day" : 6,
                  "time" : "1700"
               },
               "open" : {
                  "date" : "2022-12-03",
                  "day" : 6,
                  "time" : "0630"
               }
            }
         ],
         "weekday_text" : [
            "Monday: 6:30 AM – 5:00 PM",
            "Tuesday: 6:30 AM – 5:00 PM",
            "Wednesday: 6:30 AM – 5:00 PM",
            "Thursday: 6:30 AM – 5:00 PM",
            "Friday: 6:30 AM – 5:00 PM",
            "Saturday: 6:30 AM – 5:00 PM",
            "Sunday: 6:30 AM – 5:00 PM"
         ]
      },
      "editorial_summary" : {
         "language" : "en",
         "overview" : "Former landfill now a city recreational area with a skate park, picnicking & sports facilities."
      },
      "formatted_address" : "310 Edwin Dr, Virginia Beach, VA 23462, USA",
      "formatted_phone_number" : "(757) 385-2995",
      "geometry" : {
         "location" : {
            "lat" : 36.8312716,
            "lng" : -76.1255809
         },
         "viewport" : {
            "northeast" : {
               "lat" : 36.8329335302915,
               "lng" : -76.1243130197085
            },
            "southwest" : {
               "lat" : 36.8302355697085,
               "lng" : -76.12701098029152
            }
         }
      },
      "icon" : "https://maps.gstatic.com/mapfiles/place_api/icons/v1/png_71/park-71.png",
      "icon_background_color" : "#4DB546",
      "icon_mask_base_uri" : "https://maps.gstatic.com/mapfiles/place_api/icons/v2/tree_pinlet",
      "international_phone_number" : "+1 757-385-2995",
      "name" : "Mount Trashmore Park",
      "opening_hours" : {
         "open_now" : true,
         "periods" : [
            {
               "close" : {
                  "day" : 0,
                  "time" : "1700"
               },
               "open" : {
                  "day" : 0,
                  "time" : "0630"
               }
            },
            {
               "close" : {
                  "day" : 1,
                  "time" : "1700"
               },
               "open" : {
                  "day" : 1,
                  "time" : "0630"
               }
            },
            {
               "close" : {
                  "day" : 2,
                  "time" : "1700"
               },
               "open" : {
                  "day" : 2,
                  "time" : "0630"
               }
            },
            {
               "close" : {
                  "day" : 3,
                  "time" : "1700"
               },
               "open" : {
                  "day" : 3,
                  "time" : "0630"
               }
            },
            {
               "close" : {
                  "day" : 4,
                  "time" : "1700"
               },
               "open" : {
                  "day" : 4,
                  "time" : "0630"
               }
            },
            {
               "close" : {
                  "day" : 5,
                  "time" : "1700"
               },
               "open" : {
                  "day" : 5,
                  "time" : "0630"
               }
            },
            {
               "close" : {
                  "day" : 6,
                  "time" : "1700"
               },
               "open" : {
                  "day" : 6,
                  "time" : "0630"
               }
            }
         ],
         "weekday_text" : [
            "Monday: 6:30 AM – 5:00 PM",
            "Tuesday: 6:30 AM – 5:00 PM",
            "Wednesday: 6:30 AM – 5:00 PM",
            "Thursday: 6:30 AM – 5:00 PM",
            "Friday: 6:30 AM – 5:00 PM",
            "Saturday: 6:30 AM – 5:00 PM",
            "Sunday: 6:30 AM – 5:00 PM"
         ]
      },
      "photos" : [
         {
            "height" : 3024,
            "html_attributions" : [
               "\u003ca href=\"https://maps.google.com/maps/contrib/103362970930225337930\"\u003eBeth Maynes\u003c/a\u003e"
            ],
            "photo_reference" : "AW30NDyqIFSRXZTRIf-Q1yQtgiFJccXaFpGCue8oydF7GoR_NQebmUgsISjwC4Pc5dwlNIcRd_mrklwM-EDTAQ3040rO5bjZRTM-GY53oqgMkLO2wYZE6m98Xi4nVkd9FWPAPbfGfTUpvte2QaGb4hvRhuKAw46ANUFl38iNbq9mp3CWtneW",
            "width" : 4032
         },
         {
            "height" : 2988,
            "html_attributions" : [
               "\u003ca href=\"https://maps.google.com/maps/contrib/102094306335941117027\"\u003eKhaotic Beauty\u003c/a\u003e"
            ],
            "photo_reference" : "AW30NDyw9bmm9hCKN9Jmh3kIMuV0JefHlz9rAq3k2l4jfu0xIClAciuDu1gdgQkDTz0c9I5V-aVDT7fdP3rMJfio0FZz21AZCj7pTGO5vJlo-IkoZs-fN6uiZS8RHgV_glI038GxaDpAP40ZfBEagcSc866IDR4xLaKEcwpx6QkCGwwvmvY-",
            "width" : 5312
         },
         {
            "height" : 3000,
            "html_attributions" : [
               "\u003ca href=\"https://maps.google.com/maps/contrib/102392652282025878539\"\u003eJason Norris\u003c/a\u003e"
            ],
            "photo_reference" : "AW30NDzR3sZGjMorTeMRKpJg3TuLcCaKRxJF0Cm3p9931UIhPj7qDUqcUIKVSUpQl31sZlXDVgxiOcztO4N8easFKvPJi6ds8UYRl6_09xho48wSLliOVDMsdrnSqPSxSl74-ZmDm4kp5vGarIEHJ3liv6-QuwN0r0UYPkvUYWr8tJaJJnZ6",
            "width" : 4000
         },
         {
            "height" : 4160,
            "html_attributions" : [
               "\u003ca href=\"https://maps.google.com/maps/contrib/111829567811980066524\"\u003eAaron Tolbert\u003c/a\u003e"
            ],
            "photo_reference" : "AW30NDxdWwhB8vI9WxaWs4SPWGqB6l2k7EKSS6rgsipQWYuSP2VeDLN2KEo94UX-7E1eptvQ0v5DBSFhjegJUUT5xHsIUtII1eo7VaOr2A5eNLGdnh9EVpFqKXTMJfEbdpc4ju8gIp2P22j8csCHYJTUjWQy7lqNiNRZPgQTRZ_nQVloyC2c",
            "width" : 2340
         },
         {
            "height" : 3120,
            "html_attributions" : [
               "\u003ca href=\"https://maps.google.com/maps/contrib/107966128642278945710\"\u003eCarmen Pereira\u003c/a\u003e"
            ],
            "photo_reference" : "AW30NDwWQQiitTPf2h7Zp8rb7PKQQW6nFwCwSWt9PglyoVa8nhygmuDAVsOSJu7Q3kdUa5Uo4-RSdfkE5RhA-H15QKmsK93Yl3vuk8uPZGTgxP3ZqyiAHEIwYltEeMlLHAfeTD8ZQJdXEf0CIRneR7SHQefEupFprRV8kSixPoBbEGzk0MCr",
            "width" : 4160
         },
         {
            "height" : 4000,
            "html_attributions" : [
               "\u003ca href=\"https://maps.google.com/maps/contrib/112598382240957201052\"\u003eKeisha Peebles\u003c/a\u003e"
            ],
            "photo_reference" : "AW30NDxo2_Sh_S3QxO2tSLvDGlSUQ3rJ1CwI06k4mAS3Y3P6BhTOKcK92kwlbTIc2ru_XNxnreWJIGsO8KjEjiCbrqUfeXjQOe1geqZlDIsEg0wNsf-h9UB6fsfFi1BxiZOSRAnhR7BqISpDlhW4anx7J-idjQng1xOr_x4OcYXWtF9gnV5C",
            "width" : 3000
         },
         {
            "height" : 5464,
            "html_attributions" : [
               "\u003ca href=\"https://maps.google.com/maps/contrib/111841735265003726542\"\u003eJason Persaud\u003c/a\u003e"
            ],
            "photo_reference" : "AW30NDyJCYbhGiDENeqAmd7RQHptOLrFfQVjVjrZ3-eZTy4qogVJIIFL310RBvkoKZNY3zrvAYfdaRcdG_ZYVFppS3hGTNTUm3HY22_yIIvSH_dlEUuWvneUuXngCCyLvvc-D7RbItBuAN6g67SaNrD5SWu5YcKstZISU69eL0UzXKc0RE6g",
            "width" : 8192
         },
         {
            "height" : 12000,
            "html_attributions" : [
               "\u003ca href=\"https://maps.google.com/maps/contrib/108394052429471641497\"\u003eKyle Lewkowicz\u003c/a\u003e"
            ],
            "photo_reference" : "AW30NDypH_Cywz3eFDL72a59WheMaRRx-auKCUct7pDWzYiVAb_VDoX9ODDQcVZ_6x2yNFmicAuAtjAEymK1l6pB86XlWvG7Y5kKrQKou9Im6BBLEmZbmyZg_BCkolbhFM4AODH7BBRKHC7OzZ4KqBtaBfvJDMCu3lMR_QhO7UvsW3bdRFxc",
            "width" : 9000
         },
         {
            "height" : 2268,
            "html_attributions" : [
               "\u003ca href=\"https://maps.google.com/maps/contrib/109327609945103984790\"\u003eJuan Bueno\u003c/a\u003e"
            ],
            "photo_reference" : "AW30NDxRKXAQ0wJG9ULHdTzyjLdc0B1IjlqHJdqwnTI4N_ifPFenwKs1cZoRcsPJ4jjLUCoS03mAGLa_2Shh1Jpd0-0_cXa0nEK5yQzg3zkkp9Bv4zcem-t8sj7feAjPpS8im52C7pfaVTE661WP60r6JgR6YeiQAp5Nf16yggM4cCitoewP",
            "width" : 4032
         },
         {
            "height" : 4032,
            "html_attributions" : [
               "\u003ca href=\"https://maps.google.com/maps/contrib/107740191535779618451\"\u003eGerime Blankenship\u003c/a\u003e"
            ],
            "photo_reference" : "AW30NDxo7-2QvV2GSTXDd-1TM7ZoqZmQHPmPZw5V6KJ2N8lqOi6utDiBWidYtZNtbfEnanumhqpCjZMg2SOh0roiCLlLSJr4QSm3CfpaDefk7K3gZQYH-WlopAsot9u8VMPXfYzvnqRkYWqDDuBPhqrWlS8WYP-1UBed7YAdYYRUqh9Rw1k",
            "width" : 3024
         }
      ],
      "place_id" : "ChIJ7aZjk3uVuokRV-RK8J0MIOw",
      "plus_code" : {
         "compound_code" : "RVJF+GQ Virginia Beach, VA, USA",
         "global_code" : "8785RVJF+GQ"
      },
      "rating" : 4.7,
      "reference" : "ChIJ7aZjk3uVuokRV-RK8J0MIOw",
      "reviews" : [
         {
            "author_name" : "Luke Batiste",
            "author_url" : "https://www.google.com/maps/contrib/112297085396686464604/reviews",
            "language" : "en",
            "original_language" : "en",
            "profile_photo_url" : "https://lh3.googleusercontent.com/a-/ACNPEu-P-45rZRDBW8sHisl0Ep_9zdyL6diadRDfT2JyS_I=s128-c0x00000000-cc-rp-mo-ba5",
            "rating" : 5,
            "relative_time_description" : "a month ago",
            "text" : "Great local park with excellent facilities. Perfect for a running workout, a walk with the dog, birthday party or social gathering. One of the nicest community parks I've been to in the USA. Never felt unsafe or in danger, and always well lit. Community Gym gear available including pull up bars and such around the loop.",
            "time" : 1665095267,
            "translated" : false
         },
         {
            "author_name" : "Poshpicnixs & Events LLC VAVB",
            "author_url" : "https://www.google.com/maps/contrib/104867535406396185619/reviews",
            "language" : "en",
            "original_language" : "en",
            "profile_photo_url" : "https://lh3.googleusercontent.com/a-/ACNPEu_jzPhiTgPqlTOrVRE8AobZVdFixutyukz8ZWT84w=s128-c0x00000000-cc-rp-mo-ba3",
            "rating" : 5,
            "relative_time_description" : "4 months ago",
            "text" : "VBs favorite park! Lakeside views, track, mountain to fly your kits or have a picnic. It’s great for families, safe, clean and has plenty to do. Kids park, skate park are, riding bikes, and shelters if needed. I come here often and set up on a secluded side of the lake which offers beautiful views and a serene atmosphere. Friendly and helpful staff. Everyone keeps to themselves and does their own thing ( mostly bike riding and working out) always a good idea for walls or picnics",
            "time" : 1659451378,
            "translated" : false
         },
         {
            "author_name" : "Jason Persaud",
            "author_url" : "https://www.google.com/maps/contrib/111841735265003726542/reviews",
            "language" : "en",
            "original_language" : "en",
            "profile_photo_url" : "https://lh3.googleusercontent.com/a-/ACNPEu9eH4km_7l0X6FkBl634i_pgYWoRXYyRmP_q9fK3Q=s128-c0x00000000-cc-rp-mo",
            "rating" : 5,
            "relative_time_description" : "5 months ago",
            "text" : "Lovely park. No admission or parking fees. Lots of parking spaces in multiple lots.\n\nLots of paths, steps and hills to get a nice workout in…or a stroll.\n\nNice play area for the kids. Bathrooms and vending machines available in main parking area.",
            "time" : 1655077682,
            "translated" : false
         },
         {
            "author_name" : "nick GERARDO",
            "author_url" : "https://www.google.com/maps/contrib/113818862120663135848/reviews",
            "language" : "en",
            "original_language" : "en",
            "profile_photo_url" : "https://lh3.googleusercontent.com/a-/ACNPEu-DZSUXt-rCCMnlsT1NXVFtUGzbUbus0CqL-iqASA=s128-c0x00000000-cc-rp-mo-ba5",
            "rating" : 4,
            "relative_time_description" : "8 months ago",
            "text" : "I enjoy walking here most of the time but when it gets crowded it’s longer fun. Group s of people take up the the whole walk way. But other than that this place is great. The stairs are a great workout. I am glad this park is in my area. I do wish there was a dog park.",
            "time" : 1646952502,
            "translated" : false
         },
         {
            "author_name" : "Atiyah A",
            "author_url" : "https://www.google.com/maps/contrib/106685703716829530215/reviews",
            "language" : "en",
            "original_language" : "en",
            "profile_photo_url" : "https://lh3.googleusercontent.com/a/ALm5wu1f0Z0VQtazxGOXVRb0Q1efdIOytah_mglL5ZL3=s128-c0x00000000-cc-rp-mo-ba4",
            "rating" : 5,
            "relative_time_description" : "3 months ago",
            "text" : "Water Lantern Festival was An emotional experience to have the opportunity to remember some of that loss. To have the chance to speak the story of missing someone you lost or suffering from mental health. Please remember you are okay, and there is help.\nI Lost my son and mom; it was an honor to remember them 🥰\nNow, let me discuss the event; so much to say; you have to be there to understand.\nOn to the family fun,\nThere were a lot of vendors, music, lawn games a scavenger hunt. I enjoyed sitting near the water. I forgot to finish.\nThe food. I had Volcanic Fries, did not disappoint, and don't let the picture of my Po Boy fool you. The line speaks for itself.\nYou can find the truck at various festival",
            "time" : 1659842936,
            "translated" : false
         }
      ],
      "types" : [ "park", "tourist_attraction", "point_of_interest", "establishment" ],
      "url" : "https://maps.google.com/?cid=17014613264686572631",
      "user_ratings_total" : 7122,
      "utc_offset" : -300,
      "vicinity" : "310 Edwin Drive, Virginia Beach",
      "website" : "http://www.vbgov.com/government/departments/parks-recreation/parks-trails/city-parks/Pages/mount-trashmore-park.aspx",
      "wheelchair_accessible_entrance" : true
   },
   "status" : "OK"
}
